simple_lock/__init__.py
simple_lock/lockfile.py
simple_lock-1.0.6.dist-info/LICENSE
simple_lock-1.0.6.dist-info/METADATA
simple_lock-1.0.6.dist-info/WHEEL
simple_lock-1.0.6.dist-info/top_level.txt
simple_lock-1.0.6.dist-info/RECORD
