Metadata-Version: 2.1
Name: simple-lock
Version: 1.0.6
Summary: Simple Lockfile System.
Home-page: https://github.com/0h-n0/simple-lock
Author: Koji Ono
Author-email: kbu94982@gmail.com
License: UNKNOWN
Platform: UNKNOWN
Classifier: Programming Language :: Python :: 3.6
Classifier: Programming Language :: Python :: 3.5
Requires-Python: >=3.5
Requires-Dist: psutil
